source_stripe/__init__.py
source_stripe/manifest.yaml
source_stripe/run.py
source_stripe/schemas/accounts.json
source_stripe/schemas/application_fees.json
source_stripe/schemas/application_fees_refunds.json
source_stripe/schemas/authorizations.json
source_stripe/schemas/balance_transactions.json
source_stripe/schemas/bank_accounts.json
source_stripe/schemas/cardholders.json
source_stripe/schemas/cards.json
source_stripe/schemas/charges.json
source_stripe/schemas/checkout_sessions.json
source_stripe/schemas/checkout_sessions_line_items.json
source_stripe/schemas/coupons.json
source_stripe/schemas/credit_notes.json
source_stripe/schemas/customer_balance_transactions.json
source_stripe/schemas/customers.json
source_stripe/schemas/disputes.json
source_stripe/schemas/early_fraud_warnings.json
source_stripe/schemas/events.json
source_stripe/schemas/external_account_bank_accounts.json
source_stripe/schemas/external_account_cards.json
source_stripe/schemas/file_links.json
source_stripe/schemas/files.json
source_stripe/schemas/invoice_items.json
source_stripe/schemas/invoice_line_items.json
source_stripe/schemas/invoices.json
source_stripe/schemas/openapi_spec.json
source_stripe/schemas/payment_intents.json
source_stripe/schemas/payment_methods.json
source_stripe/schemas/payout_balance_transactions.json
source_stripe/schemas/payouts.json
source_stripe/schemas/persons.json
source_stripe/schemas/plans.json
source_stripe/schemas/prices.json
source_stripe/schemas/products.json
source_stripe/schemas/promotion_codes.json
source_stripe/schemas/refunds.json
source_stripe/schemas/reviews.json
source_stripe/schemas/setup_attempts.json
source_stripe/schemas/setup_intents.json
source_stripe/schemas/shared/address.json
source_stripe/schemas/shared/balance_transactions.json
source_stripe/schemas/shared/card.json
source_stripe/schemas/shared/cardholder.json
source_stripe/schemas/shared/customer.json
source_stripe/schemas/shared/issuing_transaction_purchase_details.json
airbyte_source_stripe-5.14.1.dist-info/METADATA
airbyte_source_stripe-5.14.1.dist-info/WHEEL
airbyte_source_stripe-5.14.1.dist-info/entry_points.txt
airbyte_source_stripe-5.14.1.dist-info/RECORD
